LICENSE.txt
MANIFEST.in
README.txt
setup.py
setup_helpers.py
django_configglue/__init__.py
django_configglue/models.py
django_configglue/schema.py
django_configglue/utils.py
django_configglue.egg-info/PKG-INFO
django_configglue.egg-info/SOURCES.txt
django_configglue.egg-info/dependency_links.txt
django_configglue.egg-info/requires.txt
django_configglue.egg-info/top_level.txt
django_configglue/management/__init__.py
django_configglue/management/commands/__init__.py
django_configglue/management/commands/settings.py
django_configglue/tests/__init__.py
django_configglue/tests/helpers.py
django_configglue/tests/settings.py
django_configglue/tests/test_configglue.py
django_configglue/tests/test_schema.py
django_configglue/tests/test_settings.py
testproject/__init__.py
testproject/main-13.cfg
testproject/main-14.cfg
testproject/main-15.cfg
testproject/main.cfg
testproject/manage.py
testproject/settings.py
testproject/testrunner.py
third-party/django/LICENSE